[1,["21ZP++nolAgaDXf/Te33uF","c9vVVc5fxNKqCQ/DSME91w","864SJsRr5CBbcmSU6Sw/29","8ap6seAthG6aaxq3dPUm3u"],["value","_textureSetter"],["cc.SpriteFrame",["cc.AnimationClip",["_name","_duration","wrapMode","curveData"],0,11]],[[1,0,1,2,3,4]],[[[{"name":"shubiao_mot_002","rect":[34,34,227,224],"offset":[-2.5,4],"originalSize":[300,300],"capInsets":[0,0,0,0]}],[0],0,[0],[1],[1]],[[{"name":"shubiao_mot_001","rect":[133,137,141,140],"offset":[53.5,-57],"originalSize":[300,300],"capInsets":[0,0,0,0]}],[0],0,[0],[1],[2]],[[[0,"dianji",0.8,22,[{},"comps",11,[{},"cc.Sprite",11,[{},"spriteFrame",12,[[[{"frame":0},"value",6,0],[{"frame":0.35},"value",6,1],[{"frame":0.7833333333333333},"value",6,2]],11,11,11]]]]]],0,0,[0,0,0],[0,0,0],[3,0,0]]]]